{"i":{"4AyDX02__":{"id":"4AyDX02__","type":"slide","setup":{"bg":{"selectedKey":"image","fill":{"opac":1,"rgb":"var(--TC3)"},"img":{"filt":{"opac":100,"gray":0,"blur":0,"tint":{"rgb":"var(--TC3)","opac":0.5,"blendMode":"multiply"}},"pos":{"type":"crop","fit":{"bg":{"color":{"rgb":"#FFF","opac":100}},"vali":"center","hali":"center"},"crop":{"poi":{"x":557,"y":450}}},"measures":{"size":{"width":1080,"height":591}}}},"transparentBg":{"selectedKey":false},"bord":{"size":0,"rad":0}}},"9vVXKdYICE":{"id":"9vVXKdYICE","type":"interactive","subtype":"interactiveRichText","setup":{"frmeTp":{"selectedKey":"rightLine"},"bg":{"selectedKey":"fill","fill":{"opac":0.2,"rgb":"#FFF"}},"txt":{"val":{"ops":[{"insert":"Tipos de variables","attributes":{"color":"#000000","lang":"ES-CO","bold":true}},{"insert":"​","attributes":{"color":"#000000"}},{"insert":"\n","attributes":{"align":"center"}},{"insert":"Cualitativas (Discretas)","attributes":{"lang":"ES-CO","color":"#000000","bold":true}},{"insert":"​","attributes":{"color":"#000000"}},{"insert":"\n","attributes":{"align":"center"}},{"insert":" ","attributes":{"lang":"ES-CO","color":"#000000","bold":true}},{"insert":"​","attributes":{"color":"#000000"}},{"insert":"\n","attributes":{"align":"justify"}},{"insert":"Sus datos son categóricos, mutuamente excluyente. No permite operaciones aritméticas. Denotan calidad (atributos y conteos) clasificados con un número fijo de categorías o clase. Se aplica estadística no parametrizada. Impera en la dicotomía observacional y en ciencias sociales.","attributes":{"lang":"ES-CO","color":"#000000"}},{"insert":"\n\n\n\n","attributes":{"align":"justify"}},{"insert":"​","attributes":{"color":"#000000"}},{"insert":"\n","attributes":{"align":"justify"}}]},"rType":"richtext"},"hali":"","paddV1":10,"vali":"middle","frmeColo":{"color":{"opac":1,"rgb":"#0b5d8c"}}}},"Jd6Vm6LiM":{"id":"Jd6Vm6LiM","type":"interactive","subtype":"interactiveRichText","setup":{"frmeTp":{"selectedKey":"rightLine"},"bg":{"selectedKey":"fill","fill":{"opac":0.2,"rgb":"#FFF"}},"txt":{"val":{"ops":[{"insert":"\n\n\n","attributes":{"align":"center"}},{"insert":"Escalas de medición","attributes":{"color":"var(--TC13)","lang":"ES-CO","bold":true}},{"insert":"\n","attributes":{"align":"center"}},{"insert":"​","attributes":{"color":"var(--TC13)"}},{"insert":"\n","attributes":{"align":"center"}},{"insert":"Nominal","attributes":{"color":"var(--TC13)","lang":"ES-CO","bold":true}},{"insert":"\n","attributes":{"align":"center"}},{"insert":"​","attributes":{"color":"var(--TC13)"}},{"insert":"\n","attributes":{"align":"center"}},{"insert":"-Admite la propiedad de la igualdad (=): reflexiva, simétrica y transitiva.","attributes":{"color":"var(--TC13)","lang":"ES-CO"}},{"insert":"\n","attributes":{"align":"justify"}},{"insert":"​","attributes":{"color":"var(--TC13)"}},{"insert":"\n","attributes":{"align":"justify"}},{"insert":"-Medición: mediante conteos ","attributes":{"lang":"ES-CO","color":"var(--TC13)"}},{"insert":"\n","attributes":{"align":"justify"}},{"insert":"(números naturales).","attributes":{"lang":"ES-CO","color":"var(--TC13)"}},{"insert":"\n","attributes":{"align":"justify"}},{"insert":"​","attributes":{"color":"var(--TC13)"}},{"insert":"\n","attributes":{"align":"justify"}},{"insert":"Ordinal","attributes":{"color":"var(--TC13)","lang":"ES-CO","bold":true}},{"insert":"\n","attributes":{"align":"center"}},{"insert":"​","attributes":{"color":"var(--TC13)"}},{"insert":"\n","attributes":{"align":"center"}},{"insert":"-Expresa relación de orden.","attributes":{"color":"var(--TC13)","lang":"ES-CO"}},{"insert":"​","attributes":{"color":"var(--TC13)"}},{"insert":"\n","attributes":{"align":"justify"}},{"insert":"-Admite la igualdad y desigualdad: irreflexiva, asimétrica, transitiva.","attributes":{"lang":"ES-CO","color":"var(--TC13)"}},{"insert":"​​","attributes":{"color":"var(--TC13)"}},{"insert":"\n\n\n\n","attributes":{"align":"justify"}}]},"rType":"richtext"},"hali":"","paddV1":21,"vali":"middle","frmeColo":{"color":{"opac":1,"rgb":"#0b5d8c"}}}},"Mwaok9UF8s":{"id":"Mwaok9UF8s","type":"interactive","subtype":"interactiveRichText","setup":{"frmeTp":{"selectedKey":"bottomLine"},"bg":{"selectedKey":"fill","fill":{"opac":0.2,"rgb":"#FFF"}},"txt":{"val":{"ops":[{"insert":"Las variables","attributes":{"bold":true,"lang":"ES-CO","color":"#0b5d8c","background":"rgba(0, 0, 0, 0)"}},{"insert":"\n","attributes":{"align":"center","size":"largeTitle"}}]},"rType":"richtext"},"vali":"middle","hali":"","frmeColo":{"color":{"opac":1,"rgb":"#0b5d8c"}}}},"BOcEuTVpA":{"id":"BOcEuTVpA","type":"interactive","subtype":"interactiveRichText","setup":{"frmeTp":{"selectedKey":"noneFrame"},"bg":{"selectedKey":"fill","fill":{"opac":0.2,"rgb":"#FFF"}},"txt":{"val":{"ops":[{"insert":"Características principales","attributes":{"lang":"ES-CO","color":"var(--TC13)","bold":true}},{"insert":"\n"},{"insert":"​","attributes":{"color":"var(--TC13)"}},{"insert":"\n"},{"insert":"Frecuencias, atributos, datos categóricos. Números, letras, símbolos, color, sexo, proporción o porcentaje. Medida de asociación: Coeficiente de contingencia.","attributes":{"lang":"ES-CO","color":"var(--TC13)"}},{"insert":"​","attributes":{"color":"var(--TC13)"}},{"insert":"\n","attributes":{"align":"justify"}},{"insert":" ","attributes":{"lang":"ES-CO","color":"var(--TC13)"}},{"insert":"​","attributes":{"color":"var(--TC13)"}},{"insert":"\n","attributes":{"align":"justify"}},{"insert":"Se determinan frecuencias.","attributes":{"lang":"ES-CO","color":"var(--TC13)"}},{"insert":"\n","attributes":{"align":"justify"}},{"insert":"​","attributes":{"color":"var(--TC13)"}},{"insert":"\n","attributes":{"align":"justify"}},{"insert":"Prueba más apropiada: la mediana.","attributes":{"lang":"ES-CO","color":"var(--TC13)"}},{"insert":"\n","attributes":{"align":"justify"}},{"insert":"​","attributes":{"color":"var(--TC13)"}},{"insert":"\n","attributes":{"align":"justify"}},{"insert":"Ingreso: alto, mediano y bajo","attributes":{"lang":"ES-CO","color":"var(--TC13)"}},{"insert":"​.","attributes":{"color":"var(--TC13)"}},{"insert":"\n\n\n","attributes":{"align":"justify"}}]},"rType":"richtext"},"paddV1":22,"vali":"middle","hali":""}}},"v":"1"}